odoo/addons/helpdesk_mgmt_portal_follower/README.rst
odoo/addons/helpdesk_mgmt_portal_follower/__init__.py
odoo/addons/helpdesk_mgmt_portal_follower/__manifest__.py
odoo/addons/helpdesk_mgmt_portal_follower/controllers/__init__.py
odoo/addons/helpdesk_mgmt_portal_follower/controllers/main.py
odoo/addons/helpdesk_mgmt_portal_follower/i18n/es.po
odoo/addons/helpdesk_mgmt_portal_follower/i18n/helpdesk_mgmt_portal_follower.pot
odoo/addons/helpdesk_mgmt_portal_follower/i18n/it.po
odoo/addons/helpdesk_mgmt_portal_follower/i18n/pt_BR.po
odoo/addons/helpdesk_mgmt_portal_follower/readme/CONTRIBUTORS.md
odoo/addons/helpdesk_mgmt_portal_follower/readme/DESCRIPTION.md
odoo/addons/helpdesk_mgmt_portal_follower/readme/ROADMAP.md
odoo/addons/helpdesk_mgmt_portal_follower/readme/USAGE.md
odoo/addons/helpdesk_mgmt_portal_follower/static/description/icon.png
odoo/addons/helpdesk_mgmt_portal_follower/static/description/index.html
odoo/addons/helpdesk_mgmt_portal_follower/tests/__init__.py
odoo/addons/helpdesk_mgmt_portal_follower/tests/test_ticket_followers.py
odoo/addons/helpdesk_mgmt_portal_follower/views/helpdesk_templates.xml
odoo_addon_helpdesk_mgmt_portal_follower-18.0.1.0.0.2.dist-info/METADATA
odoo_addon_helpdesk_mgmt_portal_follower-18.0.1.0.0.2.dist-info/WHEEL
odoo_addon_helpdesk_mgmt_portal_follower-18.0.1.0.0.2.dist-info/top_level.txt
odoo_addon_helpdesk_mgmt_portal_follower-18.0.1.0.0.2.dist-info/RECORD
